sage3reader/__init__.py
sage3reader/read_solar.py
sage3reader/sage3reader.py
sage3reader-0.2.4.dist-info/LICENSE
sage3reader-0.2.4.dist-info/METADATA
sage3reader-0.2.4.dist-info/WHEEL
sage3reader-0.2.4.dist-info/top_level.txt
sage3reader-0.2.4.dist-info/RECORD
