Metadata-Version: 2.1
Name: sage3reader
Version: 0.2.4
Summary: A python reader for SAGE III and SAGE III ISS L2 solar binary files
Home-page: http://arg.usask.ca
Author: Chris Roth
Author-email: chris.roth@usask.ca
License: MIT
Keywords: sage sageiii reader l2 binary solar
Platform: UNKNOWN
Requires-Python: >=3.6
Requires-Dist: numpy (>=1.15)
Requires-Dist: xarray (>=0.11)
